Metadata-Version: 2.1
Name: pyE2EE
Version: 5.0.4
Summary: End To End Encryption in Python.
Home-page: https://github.com/mastercodermerwin/OSOME-DB
Author: Cactochan
License: UNKNOWN
Project-URL: Bug Tracker, https://github.com/mastercodermerwin/OSOME-DB/issues
Platform: UNKNOWN
Classifier: Programming Language :: Python :: 3
Classifier: License :: OSI Approved :: MIT License
Classifier: Operating System :: OS Independent
License-File: LICENSE.txt
